bot_response_validator/__init__.py
bot_response_validator/validator.py
bot_response_validator-0.1.0.dist-info/METADATA
bot_response_validator-0.1.0.dist-info/WHEEL
bot_response_validator-0.1.0.dist-info/RECORD
