Metadata-Version: 2.1
Name: bot-response-validator
Version: 0.1.0
Summary: 
Author: Your Name
Author-email: you@example.com
Requires-Python: >=3.8,<3.12
Classifier: Programming Language :: Python :: 3
Classifier: Programming Language :: Python :: 3.8
Classifier: Programming Language :: Python :: 3.9
Classifier: Programming Language :: Python :: 3.10
Classifier: Programming Language :: Python :: 3.11
Requires-Dist: numpy (<=1.24.3)
Requires-Dist: pandas (>=2.0.3,<3.0.0)
Requires-Dist: tensorflow (>=2.13.0,<3.0.0)
Requires-Dist: transformers (>=4.31.0,<5.0.0)
